.editorconfig
.gitignore
.gitlab-ci.yml
README.rst
publish.settings.sh
publish.sh
pyproject.toml
tsconfig.json
.idea/modules.xml
.idea/peek-plugin-diagram-trace.iml
.idea/inspectionProfiles/Project_Default.xml
.idea/inspectionProfiles/profiles_settings.xml
peek_plugin_diagram_trace/__init__.py
peek_plugin_diagram_trace/plugin_package.json
peek_plugin_diagram_trace.egg-info/PKG-INFO
peek_plugin_diagram_trace.egg-info/SOURCES.txt
peek_plugin_diagram_trace.egg-info/dependency_links.txt
peek_plugin_diagram_trace.egg-info/requires.txt
peek_plugin_diagram_trace.egg-info/top_level.txt
peek_plugin_diagram_trace/_private/PluginNames.py
peek_plugin_diagram_trace/_private/__init__.py
peek_plugin_diagram_trace/_private/alembic.ini
peek_plugin_diagram_trace/_private/admin-app/diagramTrace.module.ts
peek_plugin_diagram_trace/_private/admin-app/components/diagram-trace-page/diagram-trace-page.component.html
peek_plugin_diagram_trace/_private/admin-app/components/diagram-trace-page/diagram-trace-page.component.scss
peek_plugin_diagram_trace/_private/admin-app/components/diagram-trace-page/diagram-trace-page.component.ts
peek_plugin_diagram_trace/_private/admin-app/components/edit-setting-table/edit.component.html
peek_plugin_diagram_trace/_private/admin-app/components/edit-setting-table/edit.component.scss
peek_plugin_diagram_trace/_private/admin-app/components/edit-setting-table/edit.component.ts
peek_plugin_diagram_trace/_private/alembic/__init__.py
peek_plugin_diagram_trace/_private/alembic/env.py
peek_plugin_diagram_trace/_private/alembic/script.py.mako
peek_plugin_diagram_trace/_private/alembic/versions/007ac5377946_initial_tables.py
peek_plugin_diagram_trace/_private/alembic/versions/__init__.py
peek_plugin_diagram_trace/_private/client/ClientEntryHook.py
peek_plugin_diagram_trace/_private/client/DeviceTupleDataObservableProxy.py
peek_plugin_diagram_trace/_private/client/DeviceTupleProcessorActionProxy.py
peek_plugin_diagram_trace/_private/client/__init__.py
peek_plugin_diagram_trace/_private/server/LogicEntryHook.py
peek_plugin_diagram_trace/_private/server/TupleActionProcessor.py
peek_plugin_diagram_trace/_private/server/TupleDataObservable.py
peek_plugin_diagram_trace/_private/server/__init__.py
