Metadata-Version: 2.4
Name: peek-plugin-diagram-trace
Version: 5.0.4
Summary: Peek Plugin DiagramTrace - tracing the connectivity from equipments
Author-email: Synerty <contact@synerty.com>
Project-URL: Homepage, https://github.com/Synerty/peek-plugin-diagram-trace
Keywords: Peek,Python,Platform,synerty
Requires-Dist: peek-plugin-base==5.0.4
